scalablewritingpyxel.py
scalablewritingpyxel-1.3.6.dist-info/METADATA
scalablewritingpyxel-1.3.6.dist-info/WHEEL
scalablewritingpyxel-1.3.6.dist-info/top_level.txt
scalablewritingpyxel-1.3.6.dist-info/RECORD
