Metadata-Version: 2.1
Name: scalablewritingpyxel
Version: 1.3.6
Summary: A module that give a scalable text writing function for pyxel
Home-page: https://github.com/awing-ding/pyxel_scalable_writing
Author: awing-ding
Classifier: Development Status :: 5 - Production/Stable
Classifier: Intended Audience :: Developers
Classifier: Programming Language :: Python :: 3 
Requires-Dist: pyxel
